{"status": 1, "complete": 1, "list": {"125366234": {"item_id": "125366234", "resolved_id": "125366234", "given_url": "http://domenlightenment.com/", "given_title": "", "favorite": "0", "status": "1", "time_added": "1638240363", "time_updated": "1639700549", "time_read": "1639700549", "time_favorited": "0", "sort_id": 0, "resolved_title": "Exploring the relationship between JavaScript and the modern HTML DOM", "resolved_url": "http://domenlightenment.com/", "excerpt": "You might also like: JavaScript Enlightenment An O'Reilly edited version (printed, epub, mobi, pdf) of this book is now avaliable from O'Reilly or Amazon Warning! This is the free online version of the DOM Enlightenment book in its pre-edited/draft form.", "is_article": "0", "is_index": "1", "has_video": "0", "has_image": "1", "word_count": "29054", "lang": "", "tags": {"browsers": {"item_id": "125366234", "tag": "browsers"}, "html": {"item_id": "125366234", "tag": "html"}, "javascript": {"item_id": "125366234", "tag": "javascript"}}, "image": {"item_id": "125366234", "src": "http://domenlightenment.com/images/c4sec2.png", "width": "0", "height": "0"}, "images": {"1": {"item_id": "125366234", "image_id": "1", "src": "http://domenlightenment.com/images/c4sec2.png", "width": "0", "height": "0", "credit": "", "caption": ""}, "2": {"item_id": "125366234", "image_id": "2", "src": "http://domenlightenment.com/images/c4sec2b.png", "width": "0", "height": "0", "credit": "", "caption": ""}, "3": {"item_id": "125366234", "image_id": "3", "src": "http://domenlightenment.com/images/c4sec3.png", "width": "0", "height": "0", "credit": "", "caption": ""}}, "listen_duration_estimate": 11247}, "2196063516": {"item_id": "2196063516", "resolved_id": "2196063516", "given_url": "http://mediatemple.net/blog/tips/browser-extensions-actually-use/", "given_title": "Browser Extensions I Actually Use - The Media Temple Blog", "favorite": "0", "status": "1", "time_added": "1527457939", "time_updated": "1611881990", "time_read": "1527461529", "time_favorited": "0", "sort_id": 1, "resolved_title": "Browser Extensions I Actually Use", "resolved_url": "https://mediatemple.net/blog/tips/browser-extensions-actually-use/", "excerpt": "I’m a web developer and blogger. These are the browser extensions that I actually use right now. It’s an ever-changing set, and I’m never afraid to try new ones, but I’m also fairly picky and uninstall anything I don’t find myself using.", "is_article": "0", "is_index": "0", "has_video": "0", "has_image": "1", "word_count": "989", "lang": "en", "time_to_read": 4, "top_image_url": "https://cdn2.mediatemple.net/blog/wp-content/uploads/2018/05/browserext3330x1410-8-200x200.png", "tags": {"browsers": {"item_id": "2196063516", "tag": "browsers"}, "webdev": {"item_id": "2196063516", "tag": "webdev"}}, "authors": {"99577123": {"item_id": "2196063516", "author_id": "99577123", "name": "Chris Coyier", "url": "https://mediatemple.net/blog/author/ccoyier/"}}, "image": {"item_id": "2196063516", "src": "https://d2mxuefqeaa7sj.cloudfront.net/s_81616C8C3A4FAD27C830D7FF4B36114A15F009ECC14472B306A5760AABD11E37_1525961186738_Screen+Shot+2018-05-10+at+7.06.08+AM.png", "width": "580", "height": "0"}, "images": {"1": {"item_id": "2196063516", "image_id": "1", "src": "https://d2mxuefqeaa7sj.cloudfront.net/s_81616C8C3A4FAD27C830D7FF4B36114A15F009ECC14472B306A5760AABD11E37_1525961186738_Screen+Shot+2018-05-10+at+7.06.08+AM.png", "width": "580", "height": "0", "credit": "", "caption": ""}, "2": {"item_id": "2196063516", "image_id": "2", "src": "https://d2mxuefqeaa7sj.cloudfront.net/s_81616C8C3A4FAD27C830D7FF4B36114A15F009ECC14472B306A5760AABD11E37_1525961361178_Screen+Shot+2018-05-10+at+7.08.55+AM.png", "width": "580", "height": "0", "credit": "", "caption": ""}, "3": {"item_id": "2196063516", "image_id": "3", "src": "https://d2mxuefqeaa7sj.cloudfront.net/s_81616C8C3A4FAD27C830D7FF4B36114A15F009ECC14472B306A5760AABD11E37_1525961997045_Screen+Shot+2018-05-10+at+7.19.47+AM.png", "width": "580", "height": "0", "credit": "", "caption": ""}, "4": {"item_id": "2196063516", "image_id": "4", "src": "https://d2mxuefqeaa7sj.cloudfront.net/s_81616C8C3A4FAD27C830D7FF4B36114A15F009ECC14472B306A5760AABD11E37_1525962068648_Screen+Shot+2018-05-10+at+7.20.59+AM.png", "width": "580", "height": "0", "credit": "", "caption": ""}, "5": {"item_id": "2196063516", "image_id": "5", "src": "https://d2mxuefqeaa7sj.cloudfront.net/s_81616C8C3A4FAD27C830D7FF4B36114A15F009ECC14472B306A5760AABD11E37_1525962247805_Screen+Shot+2018-05-10+at+7.23.48+AM.png", "width": "580", "height": "0", "credit": "", "caption": ""}, "6": {"item_id": "2196063516", "image_id": "6", "src": "https://d2mxuefqeaa7sj.cloudfront.net/s_81616C8C3A4FAD27C830D7FF4B36114A15F009ECC14472B306A5760AABD11E37_1525962393896_Screen+Shot+2018-05-10+at+7.25.31+AM.png", "width": "580", "height": "0", "credit": "", "caption": ""}, "7": {"item_id": "2196063516", "image_id": "7", "src": "https://d2mxuefqeaa7sj.cloudfront.net/s_81616C8C3A4FAD27C830D7FF4B36114A15F009ECC14472B306A5760AABD11E37_1525962475525_Screen+Shot+2018-05-10+at+7.27.49+AM.png", "width": "580", "height": "0", "credit": "", "caption": ""}, "8": {"item_id": "2196063516", "image_id": "8", "src": "https://d2mxuefqeaa7sj.cloudfront.net/s_81616C8C3A4FAD27C830D7FF4B36114A15F009ECC14472B306A5760AABD11E37_1525962594917_Screen+Shot+2018-05-10+at+7.29.40+AM.png", "width": "580", "height": "0", "credit": "", "caption": ""}, "9": {"item_id": "2196063516", "image_id": "9", "src": "https://d2mxuefqeaa7sj.cloudfront.net/s_81616C8C3A4FAD27C830D7FF4B36114A15F009ECC14472B306A5760AABD11E37_1525962816772_screenshot.png", "width": "580", "height": "0", "credit": "", "caption": ""}, "10": {"item_id": "2196063516", "image_id": "10", "src": "https://d2mxuefqeaa7sj.cloudfront.net/s_81616C8C3A4FAD27C830D7FF4B36114A15F009ECC14472B306A5760AABD11E37_1525962798688_s_7F1E0A8B8381ECF9169B3F0E33D7096E6312DAF9B60B0006B1FCA7AEB8AF6C53_1516023243331_ScreenShot2018-01-15at5.33.54AM.png", "width": "580", "height": "0", "credit": "", "caption": ""}, "11": {"item_id": "2196063516", "image_id": "11", "src": "https://d2mxuefqeaa7sj.cloudfront.net/s_81616C8C3A4FAD27C830D7FF4B36114A15F009ECC14472B306A5760AABD11E37_1525963113353_Screen+Shot+2018-05-10+at+7.38.23+AM.png", "width": "580", "height": "0", "credit": "", "caption": ""}, "12": {"item_id": "2196063516", "image_id": "12", "src": "https://d2mxuefqeaa7sj.cloudfront.net/s_81616C8C3A4FAD27C830D7FF4B36114A15F009ECC14472B306A5760AABD11E37_1525963328975_Screen+Shot+on+2018-05-10+at+074150.png", "width": "580", "height": "0", "credit": "", "caption": ""}, "13": {"item_id": "2196063516", "image_id": "13", "src": "https://cdn2.mediatemple.net/blog/wp-content/uploads/2016/01/me3-380x380.jpg", "width": "380", "height": "380", "credit": "", "caption": ""}}, "listen_duration_estimate": 383}, "3809752630": {"item_id": "3809752630", "resolved_id": "3809752630", "given_url": "https://antoinevastel.com/bot%20detection/2023/02/19/new-headless-chrome.html", "given_title": "", "favorite": "0", "status": "1", "time_added": "1676814544", "time_updated": "1676841109", "time_read": "1676841109", "time_favorited": "0", "sort_id": 2, "resolved_title": "New headless Chrome has been released and has a near-perfect browser fingerprint", "resolved_url": "https://antoinevastel.com/bot%20detection/2023/02/19/new-headless-chrome.html", "excerpt": "The new headless Chrome has been released in November 2022. For the moment, it hasn’t become the standard headless mode. It’s still hidden behind a --headless=new flag.", "is_article": "1", "is_index": "0", "has_video": "0", "has_image": "1", "word_count": "1350", "lang": "en", "time_to_read": 6, "tags": {"browsers": {"item_id": "3809752630", "tag": "browsers"}, "webdev": {"item_id": "3809752630", "tag": "webdev"}}, "authors": {"64485591": {"item_id": "3809752630", "author_id": "64485591", "name": "Antoine Vastel", "url": ""}}, "image": {"item_id": "3809752630", "src": "https://antoinevastel.com/assets/media/chromium-sc-headless-new0.png", "width": "0", "height": "0"}, "images": {"1": {"item_id": "3809752630", "image_id": "1", "src": "https://antoinevastel.com/assets/media/chromium-sc-headless-new0.png", "width": "0", "height": "0", "credit": "", "caption": ""}, "2": {"item_id": "3809752630", "image_id": "2", "src": "https://antoinevastel.com/assets/media/chromium-sc-headless-new.png", "width": "0", "height": "0", "credit": "", "caption": ""}, "3": {"item_id": "3809752630", "image_id": "3", "src": "https://antoinevastel.com/assets/media/chromium-sc-headless-new2.png", "width": "0", "height": "0", "credit": "", "caption": ""}}, "listen_duration_estimate": 523}, "3287091776": {"item_id": "3287091776", "resolved_id": "3287091776", "given_url": "https://blog.mozilla.org/security/2021/03/22/firefox-87-trims-http-referrers-by-default-to-protect-user-privacy/", "given_title": "", "favorite": "0", "status": "1", "time_added": "1616501579", "time_updated": "1616506874", "time_read": "1616506873", "time_favorited": "0", "sort_id": 3, "resolved_title": "Firefox 87 trims HTTP Referrers by default to protect user privacy", "resolved_url": "https://blog.mozilla.org/security/2021/03/22/firefox-87-trims-http-referrers-by-default-to-protect-user-privacy", "excerpt": "We are pleased to announce that Firefox 87 will introduce a stricter, more privacy-preserving default Referrer Policy. From now on, by default, Firefox will trim path and query string information from referrer headers to prevent sites from accidentally leaking sensitive user data.", "is_article": "1", "is_index": "0", "has_video": "0", "has_image": "0", "word_count": "507", "lang": "en", "tags": {"browsers": {"item_id": "3287091776", "tag": "browsers"}}, "domain_metadata": {"name": "Mozilla", "logo": "https://logo.clearbit.com/mozilla.org?size=800", "greyscale_logo": "https://logo.clearbit.com/mozilla.org?size=800&greyscale=true"}, "listen_duration_estimate": 196}, "2848821932": {"item_id": "2848821932", "resolved_id": "2848821932", "given_url": "https://browser.engineering/", "given_title": "Web Browser Engineering", "favorite": "0", "status": "1", "time_added": "1692273866", "time_updated": "1694562761", "time_read": "1694562761", "time_favorited": "0", "sort_id": 4, "resolved_title": "Web Browser Engineering", "resolved_url": "https://browser.engineering/", "excerpt": "Web browsers are ubiquitous, but how do they work? This book explains, building a basic but complete web browser, from networking to JavaScript, in a couple thousand lines of Python. Follow this book’s blog or Twitter for updates.", "is_article": "0", "is_index": "1", "has_video": "0", "has_image": "0", "word_count": "148", "lang": "en", "tags": {"browsers": {"item_id": "2848821932", "tag": "browsers"}, "webdev": {"item_id": "2848821932", "tag": "webdev"}}, "authors": {"144342158": {"item_id": "2848821932", "author_id": "144342158", "name": "Pavel Panchekha & Chris Harrelson", "url": ""}}, "listen_duration_estimate": 57}, "3460316176": {"item_id": "3460316176", "resolved_id": "3460316176", "given_url": "https://browser.engineering/?utm_source=pocket_mylist#", "given_title": "Web Browser Engineering", "favorite": "1", "status": "1", "time_added": "1634661841", "time_updated": "1635438225", "time_read": "1634845292", "time_favorited": "1635438225", "sort_id": 5, "resolved_title": "Web Browser Engineering", "resolved_url": "https://browser.engineering/?utm_source=pocket_mylist#", "excerpt": "Web browsers are ubiquitous, but how do they work? This book explains, building a basic but complete web browser, from networking to JavaScript, in a thousand lines of Python. Follow this book’s blog or Twitter for updates. You can also talk about the book with others in our discussion forum.", "is_article": "0", "is_index": "1", "has_video": "0", "has_image": "0", "word_count": "122", "lang": "en", "tags": {"browsers": {"item_id": "3460316176", "tag": "browsers"}, "webdev": {"item_id": "3460316176", "tag": "webdev"}}, "authors": {"144342158": {"item_id": "3460316176", "author_id": "144342158", "name": "Pavel Panchekha & Chris Harrelson", "url": ""}}, "listen_duration_estimate": 47}, "3079018135": {"item_id": "3079018135", "resolved_id": "3079018135", "given_url": "https://browser.engineering/graphics.html", "given_title": "", "favorite": "0", "status": "1", "time_added": "1639828319", "time_updated": "1640290954", "time_read": "1640290953", "time_favorited": "0", "sort_id": 6, "resolved_title": "Drawing to the Screen", "resolved_url": "https://browser.engineering/graphics.html", "excerpt": "A web browser doesn’t just download a web page; it also has to show that page to the user. In the 21st century, that means a graphical application. How does that work? In this chapter we’ll equip the toy browser with a graphical user interface.", "is_article": "0", "is_index": "0", "has_video": "0", "has_image": "0", "word_count": "3722", "lang": "en", "time_to_read": 17, "tags": {"browsers": {"item_id": "3079018135", "tag": "browsers"}, "webdev": {"item_id": "3079018135", "tag": "webdev"}}, "listen_duration_estimate": 1441}, "3552460486": {"item_id": "3552460486", "resolved_id": "3552460486", "given_url": "https://browser.engineering/scheduling.html", "given_title": "", "favorite": "0", "status": "1", "time_added": "1645379986", "time_updated": "1645380681", "time_read": "1645380681", "time_favorited": "0", "sort_id": 7, "resolved_title": "Scheduling Tasks and Threads", "resolved_url": "https://browser.engineering/scheduling.html", "excerpt": "Modern browsers must run sophisticated applications while staying responsive to user actions. Doing so means choosing which of its many tasks to prioritize and which to delay until later—tasks like JavaScript callbacks, user input, and rendering.", "is_article": "0", "is_index": "0", "has_video": "0", "has_image": "0", "word_count": "10061", "lang": "en", "time_to_read": 46, "tags": {"browsers": {"item_id": "3552460486", "tag": "browsers"}, "webdev": {"item_id": "3552460486", "tag": "webdev"}}, "listen_duration_estimate": 3895}, "3934763198": {"item_id": "3934763198", "resolved_id": "3934736914", "given_url": "https://browserbook.substack.com/p/adding-a-url-class?r=oc5d&utm_medium=email", "given_title": "Adding a URL class", "favorite": "0", "status": "1", "time_added": "1694627580", "time_updated": "1694647267", "time_read": "1694647267", "time_favorited": "0", "sort_id": 8, "resolved_title": "Adding a URL class", "resolved_url": "https://browserbook.substack.com/p/adding-a-url-class", "excerpt": "Hi all! Now that Chris & I have finished all of the chapters in the book, we’re going back through earlier chapters and trying to fix anything that turned out to be a bad idea.", "is_article": "1", "is_index": "0", "has_video": "0", "has_image": "0", "word_count": "1122", "lang": "en", "time_to_read": 5, "top_image_url": "https://substackcdn.com/image/fetch/f_auto,q_auto:best,fl_progressive:steep/https%3A%2F%2Fbrowserbook.substack.com%2Ftwitter%2Fsubscribe-card.jpg%3Fv%3D-1338915068%26version%3D9", "tags": {"browsers": {"item_id": "3934763198", "tag": "browsers"}, "webdev": {"item_id": "3934763198", "tag": "webdev"}}, "authors": {"5454083": {"item_id": "3934763198", "author_id": "5454083", "name": "Pavel Panchekha", "url": ""}}, "listen_duration_estimate": 434}, "3903702649": {"item_id": "3903702649", "resolved_id": "3903702651", "given_url": "https://browserbook.substack.com/p/chapter-16-reusing-previous-computations?utm_medium=email", "given_title": "Chapter 16: Reusing Previous Computations", "favorite": "0", "status": "1", "time_added": "1689382076", "time_updated": "1690156781", "time_read": "1690156781", "time_favorited": "0", "sort_id": 9, "resolved_title": "Chapter 16: Reusing Previous Computations", "resolved_url": "https://browserbook.substack.com/p/chapter-16-reusing-previous-computations", "excerpt": "Chapter 16, Reusing Previous Computations, is now finished! This chapter focuses on invalidation, a technique that browsers use to avoid rendering work and speed up interactions. Invalidation is well known to be a nest of bugs, performance issues, and subtle interactions.", "is_article": "1", "is_index": "0", "has_video": "0", "has_image": "0", "word_count": "388", "lang": "en", "top_image_url": "https://substackcdn.com/image/fetch/f_auto,q_auto:best,fl_progressive:steep/https%3A%2F%2Fbrowserbook.substack.com%2Ftwitter%2Fsubscribe-card.jpg%3Fv%3D-1338915068%26version%3D9", "tags": {"browsers": {"item_id": "3903702649", "tag": "browsers"}, "webdev": {"item_id": "3903702649", "tag": "webdev"}}, "authors": {"5454083": {"item_id": "3903702649", "author_id": "5454083", "name": "Pavel Panchekha", "url": ""}}, "listen_duration_estimate": 150}, "3243175695": {"item_id": "3243175695", "resolved_id": "3243175695", "given_url": "https://cujo.com/building-an-advanced-fingerprinting-detector-ai/", "given_title": "", "favorite": "0", "status": "1", "time_added": "1612004947", "time_updated": "1612005792", "time_read": "1612005792", "time_favorited": "0", "sort_id": 10, "resolved_title": "Building an Advanced Fingerprinting Detector AI", "resolved_url": "https://cujo.com/building-an-advanced-fingerprinting-detector-ai/", "excerpt": "In two earlier posts, we introduced the problem of browser fingerprinting and showed a static fingerprinting detector AI that is based on the raw text content of JavaScript files. Now we will refine the solution and take the dynamic behavior of JavaScript files into account. Did you know 65.", "is_article": "1", "is_index": "0", "has_video": "0", "has_image": "1", "word_count": "1540", "lang": "en", "time_to_read": 7, "top_image_url": "https://cujo.com/wp-content/uploads/2021/01/word-image.png", "tags": {"browsers": {"item_id": "3243175695", "tag": "browsers"}, "webdev": {"item_id": "3243175695", "tag": "webdev"}}, "authors": {"1669905": {"item_id": "3243175695", "author_id": "1669905", "name": "Gábor Takács", "url": ""}}, "image": {"item_id": "3243175695", "src": "https://cujo.com/wp-content/uploads/2021/01/word-image.png", "width": "1119", "height": "489"}, "images": {"1": {"item_id": "3243175695", "image_id": "1", "src": "https://cujo.com/wp-content/uploads/2021/01/word-image.png", "width": "1119", "height": "489", "credit": "", "caption": ""}, "2": {"item_id": "3243175695", "image_id": "2", "src": "https://cujo.com/wp-content/uploads/2021/01/word-image-1.png", "width": "557", "height": "436", "credit": "", "caption": ""}}, "listen_duration_estimate": 596}, "3828471439": {"item_id": "3828471439", "resolved_id": "3828471439", "given_url": "https://dev.to/ruppysuppy/deep-dive-into-how-web-browsers-work-with-illustrations-249b", "given_title": "", "favorite": "0", "status": "1", "time_added": "1679491545", "time_updated": "1679505374", "time_read": "1679505373", "time_favorited": "0", "sort_id": 11, "resolved_title": "", "resolved_url": "https://dev.to/ruppysuppy/deep-dive-into-how-web-browsers-work-with-illustrations-249b", "excerpt": "", "is_article": "0", "is_index": "0", "has_video": "0", "has_image": "0", "word_count": "0", "lang": "", "tags": {"browsers": {"item_id": "3828471439", "tag": "browsers"}, "css": {"item_id": "3828471439", "tag": "css"}, "html": {"item_id": "3828471439", "tag": "html"}, "ui-ux": {"item_id": "3828471439", "tag": "ui-ux"}, "webdev": {"item_id": "3828471439", "tag": "webdev"}}, "domain_metadata": {"name": "The Practical Dev", "logo": "https://logo.clearbit.com/dev.to?size=800", "greyscale_logo": "https://logo.clearbit.com/dev.to?size=800&greyscale=true"}, "listen_duration_estimate": 0}, "550693558": {"item_id": "550693558", "resolved_id": "550693558", "given_url": "https://developer.chrome.com/extensions/getstarted", "given_title": "Getting Started Tutorial - Google Chrome", "favorite": "0", "status": "1", "time_added": "1547835476", "time_updated": "1611881990", "time_read": "1548214398", "time_favorited": "0", "sort_id": 12, "resolved_title": "Getting started", "resolved_url": "https://developer.chrome.com/extensions/getstarted", "excerpt": "Extensions are made of different, but cohesive, components. Components can include background scripts, content scripts, an options page, UI elements and various logic files. Extension components are created with web development technologies: HTML, CSS, and JavaScript.", "is_article": "1", "is_index": "0", "has_video": "0", "has_image": "1", "word_count": "1770", "lang": "en", "time_to_read": 8, "top_image_url": "https://wd.imgix.net/image/foR0vJZKULb5AGJExlazy1xYDgI2/xvNiBdV0ZwwLUE4SEdbf.png?auto=format&w=1521", "tags": {"browsers": {"item_id": "550693558", "tag": "browsers"}}, "image": {"item_id": "550693558", "src": "https://wd.imgix.net/image/BhuKGJaIeLNPW9ehns59NfwqKxF2/vOu7iPbaapkALed96rzN.png?auto=format", "width": "563", "height": "355"}, "images": {"1": {"item_id": "550693558", "image_id": "1", "src": "https://wd.imgix.net/image/BhuKGJaIeLNPW9ehns59NfwqKxF2/vOu7iPbaapkALed96rzN.png?auto=format", "width": "563", "height": "355", "credit": "", "caption": ""}, "2": {"item_id": "550693558", "image_id": "2", "src": "https://wd.imgix.net/image/BhuKGJaIeLNPW9ehns59NfwqKxF2/dx9EpIKK949olhe8qraK.png?auto=format", "width": "566", "height": "353", "credit": "", "caption": ""}, "3": {"item_id": "550693558", "image_id": "3", "src": "https://wd.imgix.net/image/BhuKGJaIeLNPW9ehns59NfwqKxF2/GdHNy255kS4hWD5vb1fc.png?auto=format", "width": "502", "height": "278", "credit": "", "caption": ""}, "4": {"item_id": "550693558", "image_id": "4", "src": "https://wd.imgix.net/image/BhuKGJaIeLNPW9ehns59NfwqKxF2/ku5Z8MMssgw6MKctpJVI.png?auto=format", "width": "187", "height": "153", "credit": "", "caption": ""}, "5": {"item_id": "550693558", "image_id": "5", "src": "https://wd.imgix.net/image/BhuKGJaIeLNPW9ehns59NfwqKxF2/aV46PP8KCjEqqenSJxxp.png?auto=format", "width": "248", "height": "260", "credit": "", "caption": ""}}, "listen_duration_estimate": 685}, "1406727381": {"item_id": "1406727381", "resolved_id": "1406727381", "given_url": "https://developer.mozilla.org/en-US/docs/Learn/HTML/Multimedia_and_embedding/Responsive_images", "given_title": "", "favorite": "0", "status": "1", "time_added": "1638240363", "time_updated": "1640552900", "time_read": "1640552900", "time_favorited": "0", "sort_id": 13, "resolved_title": "Responsive images", "resolved_url": "https://developer.mozilla.org/en-US/docs/Learn/HTML/Multimedia_and_embedding/Responsive_images", "excerpt": "Mozilla splash page Source on GitHub Report a problem with this content on GitHub Want to fix the problem yourself? See our Contribution guide.", "is_article": "1", "is_index": "0", "has_video": "0", "has_image": "1", "word_count": "24", "lang": "en", "top_image_url": "https://developer.mozilla.org/mdn-social-share.2f09512a.png", "tags": {"browsers": {"item_id": "1406727381", "tag": "browsers"}, "images": {"item_id": "1406727381", "tag": "images"}, "webdev": {"item_id": "1406727381", "tag": "webdev"}}, "authors": {"145924320": {"item_id": "1406727381", "author_id": "145924320", "name": "MDN", "url": "https://developer.mozilla.org/en-US/docs/Learn/HTML/Multimedia_and_embedding/Responsive_images/contributors.txt"}}, "image": {"item_id": "1406727381", "src": "https://developer.mozilla.org/en-US/docs/Learn/HTML/Multimedia_and_embedding/Responsive_images/resolution-example.png", "width": "480", "height": "425"}, "images": {"1": {"item_id": "1406727381", "image_id": "1", "src": "https://developer.mozilla.org/en-US/docs/Learn/HTML/Multimedia_and_embedding/Responsive_images/resolution-example.png", "width": "480", "height": "425", "credit": "", "caption": ""}}, "domain_metadata": {"name": "Mozilla", "logo": "https://logo.clearbit.com/mozilla.org?size=800", "greyscale_logo": "https://logo.clearbit.com/mozilla.org?size=800&greyscale=true"}, "listen_duration_estimate": 9}, "608917334": {"item_id": "608917334", "resolved_id": "608917334", "given_url": "https://developer.mozilla.org/en-US/docs/Web/API/CSS_Object_Model", "given_title": "", "favorite": "0", "status": "1", "time_added": "1638240363", "time_updated": "1641264547", "time_read": "1641264548", "time_favorited": "0", "sort_id": 14, "resolved_title": "CSS Object Model (CSSOM)", "resolved_url": "https://developer.mozilla.org/en-US/docs/Web/API/CSS_Object_Model", "excerpt": "The CSS Object Model is a set of APIs allowing the manipulation of CSS from JavaScript. It is much like the DOM, but for the CSS rather than the HTML. It allows users to read and modify CSS style dynamically. The values of CSS are represented untyped, that is using String objects.", "is_article": "1", "is_index": "0", "has_video": "0", "has_image": "0", "word_count": "362", "lang": "en", "top_image_url": "https://developer.mozilla.org/mdn-social-share.0ca9dbda.png", "tags": {"browsers": {"item_id": "608917334", "tag": "browsers"}, "css": {"item_id": "608917334", "tag": "css"}, "webdev": {"item_id": "608917334", "tag": "webdev"}}, "authors": {"152860682": {"item_id": "608917334", "author_id": "152860682", "name": "MDN", "url": "https://developer.mozilla.org/en-US/docs/Web/API/CSS_Object_Model/contributors.txt"}}, "domain_metadata": {"name": "Mozilla", "logo": "https://logo.clearbit.com/mozilla.org?size=800", "greyscale_logo": "https://logo.clearbit.com/mozilla.org?size=800&greyscale=true"}, "listen_duration_estimate": 140}, "1005092219": {"item_id": "1005092219", "resolved_id": "3288738417", "given_url": "https://developers.google.com/web/tools/chrome-devtools/", "given_title": "", "favorite": "0", "status": "1", "time_added": "1638240363", "time_updated": "1640553044", "time_read": "1640553043", "time_favorited": "0", "sort_id": 15, "resolved_title": "Chrome DevTools", "resolved_url": "https://developer.chrome.com/docs/devtools/", "excerpt": "Chrome DevTools is a set of web developer tools built directly into the Google Chrome browser.", "is_article": "0", "is_index": "1", "has_video": "0", "has_image": "0", "word_count": "0", "lang": "", "top_image_url": "https://wd.imgix.net/image/fuiz5I8Iv7bV8YbrK2PKiY3Vask2/iGPiWTtoy7iF932Xday1.png?auto=format&w=1521", "tags": {"browsers": {"item_id": "1005092219", "tag": "browsers"}, "webdev": {"item_id": "1005092219", "tag": "webdev"}}, "listen_duration_estimate": 0}, "3414388009": {"item_id": "3414388009", "resolved_id": "3414388009", "given_url": "https://frankgroeneveld.nl/2021/08/24/most-underused-browser-feature/", "given_title": "", "favorite": "0", "status": "1", "time_added": "1629939505", "time_updated": "1630192402", "time_read": "1630192403", "time_favorited": "0", "sort_id": 16, "resolved_title": "The most underused browser feature", "resolved_url": "https://frankgroeneveld.nl/2021/08/24/most-underused-browser-feature/", "excerpt": "The web has been plagued by cookie consent popups and banners since the General Data Protection Regulation (GDPR) has come into effect. See for yourself when you visit articles like this and this.", "is_article": "1", "is_index": "0", "has_video": "0", "has_image": "0", "word_count": "226", "lang": "en", "tags": {"browsers": {"item_id": "3414388009", "tag": "browsers"}, "webdev": {"item_id": "3414388009", "tag": "webdev"}}, "listen_duration_estimate": 87}, "3194426382": {"item_id": "3194426382", "resolved_id": "3194426382", "given_url": "https://github.com/ArchiveBox/ArchiveBox/wiki/Usage#Import-list-of-links-from-browser-history", "given_title": "Usage · ArchiveBox/ArchiveBox Wiki · GitHub", "favorite": "0", "status": "1", "time_added": "1656020226", "time_updated": "1706833159", "time_read": "1656026013", "time_favorited": "0", "sort_id": 17, "resolved_title": "Usage", "resolved_url": "https://github.com/ArchiveBox/ArchiveBox/wiki/Usage#Import-a-list-of-URLs-from-a-text-file", "excerpt": "Usage Usage CLI Usage: Docs and examples for the ArchiveBox command line interface. UI Usage: Docs and screenshots for the outputted HTML archive interface. Disk Layout: Description of the archive folder structure and contents.", "is_article": "1", "is_index": "0", "has_video": "0", "has_image": "1", "word_count": "146", "lang": "en", "top_image_url": "https://repository-images.githubusercontent.com/90356372/6ce4d400-6129-11e9-9898-707bd6d5df76", "tags": {"browsers": {"item_id": "3194426382", "tag": "browsers"}, "programming": {"item_id": "3194426382", "tag": "programming"}, "python": {"item_id": "3194426382", "tag": "python"}, "web-crawlers": {"item_id": "3194426382", "tag": "web-crawlers"}}, "image": {"item_id": "3194426382", "src": "https://camo.githubusercontent.com/5a26c1ed205bb3ad02a0c179d9f8e193d38cc39bcacffc34ac84b6966562ef23/68747470733a2f2f692e696d6775722e636f6d2f50564f3838415a2e706e67", "width": "0", "height": "0"}, "images": {"1": {"item_id": "3194426382", "image_id": "1", "src": "https://camo.githubusercontent.com/5a26c1ed205bb3ad02a0c179d9f8e193d38cc39bcacffc34ac84b6966562ef23/68747470733a2f2f692e696d6775722e636f6d2f50564f3838415a2e706e67", "width": "0", "height": "0", "credit": "", "caption": ""}, "2": {"item_id": "3194426382", "image_id": "2", "src": "https://camo.githubusercontent.com/b00cf1d8c2d3f8737c941b342f86a1b08963ab8701e16856812993dc6a8f6417/68747470733a2f2f692e696d6775722e636f6d2f346e6b466a64762e706e67", "width": "0", "height": "30", "credit": "", "caption": ""}, "3": {"item_id": "3194426382", "image_id": "3", "src": "https://camo.githubusercontent.com/90bc908826728c0e4261acfff5619fd732c7be2b2a00624fce6363c9a3623c90/68747470733a2f2f696d672e736869656c64732e696f2f747769747465722f75726c2f687474702f736869656c64732e696f2e7376673f7374796c653d736f6369616c", "width": "0", "height": "0", "credit": "", "caption": ""}, "4": {"item_id": "3194426382", "image_id": "4", "src": "https://camo.githubusercontent.com/2207dd0a5bc5bd9c5c5da2227eb5ebbb1cc78c06ac9d80c986f38fb0a068da51/68747470733a2f2f696d672e736869656c64732e696f2f62616467652f537570706f7274253230646576656c6f706d656e742d50617472656f6e2d2532334444354437362e737667", "width": "0", "height": "0", "credit": "", "caption": ""}, "5": {"item_id": "3194426382", "image_id": "5", "src": "https://camo.githubusercontent.com/f96ddf989704970baff9f608dd5be65295cfaf70f010820deac91568d3612938/68747470733a2f2f692e696d6775722e636f6d2f38793668765a612e706e67", "width": "0", "height": "0", "credit": "", "caption": ""}}, "domain_metadata": {"name": "GitHub", "logo": "https://logo.clearbit.com/github.com?size=800", "greyscale_logo": "https://logo.clearbit.com/github.com?size=800&greyscale=true"}, "listen_duration_estimate": 57}, "2388619438": {"item_id": "2388619438", "resolved_id": "2388619438", "given_url": "https://hacks.mozilla.org/2018/11/the-power-of-web-components/", "given_title": "The Power of Web Components - Mozilla Hacks - the Web developer blog", "favorite": "0", "status": "1", "time_added": "1542341383", "time_updated": "1611881990", "time_read": "1542424179", "time_favorited": "0", "sort_id": 18, "resolved_title": "The Power of Web Components – Mozilla Hacks : the Web developer blog", "resolved_url": "https://hacks.mozilla.org/2018/11/the-power-of-web-components", "excerpt": "Ever since the first animated DHTML cursor trails and “Site of the Week” badges graced the web, re-usable code has been a temptation for web developers. And ever since those heady days, integrating third-party UI into your site has been, well, a semi-brittle headache.", "is_article": "1", "is_index": "0", "has_video": "0", "has_image": "1", "word_count": "2078", "lang": "en", "time_to_read": 9, "top_image_url": "https://hacks.mozilla.org/files/2018/11/webcomponents-peek.png", "tags": {"browsers": {"item_id": "2388619438", "tag": "browsers"}, "webdev": {"item_id": "2388619438", "tag": "webdev"}}, "image": {"item_id": "2388619438", "src": "https://2r4s9p1yi1fa2jd7j43zph8r-wpengine.netdna-ssl.com/files/2018/11/webcomponents-peek.png", "width": "1280", "height": "816"}, "images": {"1": {"item_id": "2388619438", "image_id": "1", "src": "https://2r4s9p1yi1fa2jd7j43zph8r-wpengine.netdna-ssl.com/files/2018/11/webcomponents-peek.png", "width": "1280", "height": "816", "credit": "", "caption": ""}}, "domain_metadata": {"name": "Mozilla", "logo": "https://logo.clearbit.com/mozilla.org?size=800", "greyscale_logo": "https://logo.clearbit.com/mozilla.org?size=800&greyscale=true"}, "listen_duration_estimate": 804}, "448647155": {"item_id": "448647155", "resolved_id": "448647155", "given_url": "https://hpbn.co/", "given_title": "", "favorite": "0", "status": "1", "time_added": "1684343575", "time_updated": "1690159031", "time_read": "1690159031", "time_favorited": "0", "sort_id": 19, "resolved_title": "High Performance Browser Networking", "resolved_url": "https://hpbn.co/", "excerpt": "Performance is a feature. This book provides a hands-on overview of what every web developer needs to know about the various types of networks (WiFi, 3G/4G), transport protocols (UDP, TCP, and TLS), application protocols (HTTP/1.", "is_article": "0", "is_index": "1", "has_video": "0", "has_image": "0", "word_count": "145", "lang": "", "top_image_url": "https://hpbn.co/assets/twitter.jpg", "tags": {"browsers": {"item_id": "448647155", "tag": "browsers"}, "webdev": {"item_id": "448647155", "tag": "webdev"}}, "listen_duration_estimate": 56}, "2341733544": {"item_id": "2341733544", "resolved_id": "2341733544", "given_url": "https://medium.com/datadriveninvestor/stopping-using-console-log-and-start-using-your-browsers-debugger-62bc893d93ff", "given_title": "How to stop using console.log() and start using your browser’s debugger", "favorite": "0", "status": "1", "time_added": "1540339956", "time_updated": "1706470112", "time_read": "1540497350", "time_favorited": "0", "sort_id": 20, "resolved_title": "How to stop using console.log() and start using your browser’s debugger", "resolved_url": "https://medium.com/datadriveninvestor/stopping-using-console-log-and-start-using-your-browsers-debugger-62bc893d93ff", "excerpt": "When I started my journey to become a software developer, I definitely ran into my fair share of bumps in the road. One of the most common struggles that most new developers face is debugging.", "is_article": "1", "is_index": "0", "has_video": "0", "has_image": "1", "word_count": "1164", "lang": "en", "time_to_read": 5, "top_image_url": "https://miro.medium.com/max/1102/1*boS5jNmWpJQMc4o5VHReWA.png", "tags": {"browsers": {"item_id": "2341733544", "tag": "browsers"}, "debugging": {"item_id": "2341733544", "tag": "debugging"}, "javascript": {"item_id": "2341733544", "tag": "javascript"}}, "authors": {"96525773": {"item_id": "2341733544", "author_id": "96525773", "name": "Parag Zaveri", "url": "https://medium.com/@parag.g.zaveri"}}, "image": {"item_id": "2341733544", "src": "https://miro.medium.com/max/1600/0*rS4PXXRYoTgWKg27", "width": "700", "height": "60"}, "images": {"1": {"item_id": "2341733544", "image_id": "1", "src": "https://miro.medium.com/max/1600/0*rS4PXXRYoTgWKg27", "width": "700", "height": "60", "credit": "", "caption": ""}, "2": {"item_id": "2341733544", "image_id": "2", "src": "https://miro.medium.com/max/1600/1*r-TVPOq2bvKB1clw9vgCHg.png", "width": "416", "height": "638", "credit": "", "caption": ""}, "3": {"item_id": "2341733544", "image_id": "3", "src": "https://miro.medium.com/max/1690/1*t3SETtaOVas1trQfjRO4gw.png", "width": "845", "height": "941", "credit": "", "caption": ""}, "4": {"item_id": "2341733544", "image_id": "4", "src": "https://miro.medium.com/max/1600/1*ZLrHNgLfA0_ImUT-bjiN-w.png", "width": "664", "height": "430", "credit": "", "caption": ""}, "5": {"item_id": "2341733544", "image_id": "5", "src": "https://miro.medium.com/max/1600/1*HaePgs1Jyqw1L-wcCiQk0A.png", "width": "26", "height": "30", "credit": "", "caption": "Step into next function call"}, "6": {"item_id": "2341733544", "image_id": "6", "src": "https://miro.medium.com/max/1600/1*07byHc3enj1vgrapehg4Bg.png", "width": "29", "height": "28", "credit": "", "caption": "Step over next function call"}, "7": {"item_id": "2341733544", "image_id": "7", "src": "https://miro.medium.com/max/1600/1*EfVOw-IfVMScANFDGn92mw.png", "width": "678", "height": "938", "credit": "", "caption": ""}, "8": {"item_id": "2341733544", "image_id": "8", "src": "https://miro.medium.com/max/2204/1*boS5jNmWpJQMc4o5VHReWA.png", "width": "1102", "height": "937", "credit": "", "caption": ""}, "9": {"item_id": "2341733544", "image_id": "9", "src": "https://miro.medium.com/max/1672/1*kQDNWSdmUhXrpFyOaY9vHA.png", "width": "836", "height": "912", "credit": "", "caption": ""}, "10": {"item_id": "2341733544", "image_id": "10", "src": "https://miro.medium.com/max/1686/1*Bg6oJPpIZKnBywUG3U_l1w.png", "width": "843", "height": "878", "credit": "", "caption": ""}, "11": {"item_id": "2341733544", "image_id": "11", "src": "https://miro.medium.com/max/2114/1*NPHg0e_aRlVkNYEbQQCITw.png", "width": "1057", "height": "508", "credit": "", "caption": ""}, "12": {"item_id": "2341733544", "image_id": "12", "src": "https://miro.medium.com/max/2340/1*WPiRbg5uZXh11NCxr1U_2A.png", "width": "1170", "height": "1244", "credit": "", "caption": ""}}, "domain_metadata": {"name": "Medium", "logo": "https://logo.clearbit.com/medium.com?size=800", "greyscale_logo": "https://logo.clearbit.com/medium.com?size=800&greyscale=true"}, "listen_duration_estimate": 451}, "3838574699": {"item_id": "3838574699", "resolved_id": "3838574699", "given_url": "https://mullvad.net/en/browser", "given_title": "Free the internet from mass surveillance. With the Mullvad Browser.", "favorite": "0", "status": "1", "time_added": "1680537559", "time_updated": "1680714168", "time_read": "1680714168", "time_favorited": "0", "sort_id": 21, "resolved_title": "Free the internet from mass surveillance. With the Mullvad Browser.", "resolved_url": "https://mullvad.net/en/browser", "excerpt": "The Mullvad Browser is a privacy-focused web browser developed in collaboration between Mullvad VPN and the Tor Project. It’s produced to minimize tracking and fingerprinting. You could say it’s a Tor Browser to use without the Tor Network.", "is_article": "0", "is_index": "1", "has_video": "0", "has_image": "0", "word_count": "0", "lang": "en", "top_image_url": "https://mullvad.net/images/browser-og.jpg", "tags": {"browsers": {"item_id": "3838574699", "tag": "browsers"}, "security": {"item_id": "3838574699", "tag": "security"}}, "listen_duration_estimate": 0}, "3013196396": {"item_id": "3013196396", "resolved_id": "3013196396", "given_url": "https://nyxt.atlas.engineer/", "given_title": "Nyxt", "favorite": "0", "status": "1", "time_added": "1616415645", "time_updated": "1706833159", "time_read": "1616441486", "time_favorited": "0", "sort_id": 22, "resolved_title": "the hacker's browser.", "resolved_url": "https://nyxt.atlas.engineer/", "excerpt": "Navigate large documents with ease. Fuzzily search through headings. Utilize the power of running commands against multiple objects to avoid repeating yourself. In the example below, we select and close all buffers that match the string \"ele\".", "is_article": "0", "is_index": "1", "has_video": "0", "has_image": "1", "word_count": "234", "lang": "en", "tags": {"browsers": {"item_id": "3013196396", "tag": "browsers"}, "programming": {"item_id": "3013196396", "tag": "programming"}, "webdev": {"item_id": "3013196396", "tag": "webdev"}}, "image": {"item_id": "3013196396", "src": "https://nyxt.atlas.engineer/image/animation/jump-heading.png", "width": "0", "height": "0"}, "images": {"1": {"item_id": "3013196396", "image_id": "1", "src": "https://nyxt.atlas.engineer/image/animation/jump-heading.png", "width": "0", "height": "0", "credit": "", "caption": ""}, "2": {"item_id": "3013196396", "image_id": "2", "src": "https://nyxt.atlas.engineer/image/animation/kill-buffers.png", "width": "0", "height": "0", "credit": "", "caption": ""}, "3": {"item_id": "3013196396", "image_id": "3", "src": "https://nyxt.atlas.engineer/image/animation/execute-commands.png", "width": "0", "height": "0", "credit": "", "caption": ""}, "4": {"item_id": "3013196396", "image_id": "4", "src": "https://nyxt.atlas.engineer/image/animation/switch-buffer.png", "width": "0", "height": "0", "credit": "", "caption": ""}, "5": {"item_id": "3013196396", "image_id": "5", "src": "https://nyxt.atlas.engineer/image/animation/element-hint.png", "width": "0", "height": "0", "credit": "", "caption": ""}, "6": {"item_id": "3013196396", "image_id": "6", "src": "https://nyxt.atlas.engineer/image/animation/lisp-repl.png", "width": "0", "height": "0", "credit": "", "caption": ""}, "7": {"item_id": "3013196396", "image_id": "7", "src": "https://nyxt.atlas.engineer/image/animation/bookmark-search.png", "width": "0", "height": "0", "credit": "", "caption": ""}, "8": {"item_id": "3013196396", "image_id": "8", "src": "https://nyxt.atlas.engineer/image/animation/auto-fill.png", "width": "0", "height": "0", "credit": "", "caption": ""}, "9": {"item_id": "3013196396", "image_id": "9", "src": "https://nyxt.atlas.engineer/image/animation/paste-ring.png", "width": "0", "height": "0", "credit": "", "caption": ""}, "10": {"item_id": "3013196396", "image_id": "10", "src": "https://nyxt.atlas.engineer/image/animation/history.png", "width": "0", "height": "0", "credit": "", "caption": ""}}, "listen_duration_estimate": 91}, "3216922830": {"item_id": "3216922830", "resolved_id": "3216922830", "given_url": "https://omar.website/tabfs/", "given_title": "TabFS", "favorite": "0", "status": "1", "time_added": "1609514806", "time_updated": "1706833159", "time_read": "1609592671", "time_favorited": "0", "sort_id": 23, "resolved_title": "TabFS", "resolved_url": "https://omar.website/tabfs/", "excerpt": "TabFS is a browser extension that mounts your browser tabs as a filesystem on your computer. Each of your open tabs is mapped to a folder.", "is_article": "1", "is_index": "1", "has_video": "1", "has_image": "1", "word_count": "3484", "lang": "en", "time_to_read": 16, "top_image_url": "https://omar.website/projects/tabfs.png", "tags": {"browsers": {"item_id": "3216922830", "tag": "browsers"}, "programming": {"item_id": "3216922830", "tag": "programming"}}, "image": {"item_id": "3216922830", "src": "https://omar.website/tabfs/doc/00-browser.png", "width": "0", "height": "0"}, "images": {"1": {"item_id": "3216922830", "image_id": "1", "src": "https://omar.website/tabfs/doc/00-browser.png", "width": "0", "height": "0", "credit": "", "caption": "Going through the files inside a tab's folder. For example, the url.txt, text.txt, and title.txt files tell me those live properties of this tab"}, "2": {"item_id": "3216922830", "image_id": "2", "src": "https://omar.website/tabfs/doc/00-finder.png", "width": "0", "height": "0", "credit": "", "caption": "I have 3 tabs open, and they map to 3 folders in TabFS"}, "3": {"item_id": "3216922830", "image_id": "3", "src": "https://omar.website/tabfs/doc/inspector.png", "width": "0", "height": "0", "credit": "", "caption": ""}, "4": {"item_id": "3216922830", "image_id": "4", "src": "https://omar.website/tabfs/oss-capital.png", "width": "0", "height": "0", "credit": "", "caption": ""}}, "videos": {"1": {"item_id": "3216922830", "video_id": "1", "src": "https://omar.website/tabfs/doc/finder-contents.mp4", "width": "0", "height": "0", "type": "5", "vid": "", "length": "0"}, "2": {"item_id": "3216922830", "video_id": "2", "src": "https://omar.website/tabfs/doc/delete.mp4", "width": "0", "height": "0", "type": "5", "vid": "", "length": "0"}}, "listen_duration_estimate": 1349}, "3560529951": {"item_id": "3560529951", "resolved_id": "3560529951", "given_url": "https://oxylabs.io/blog/what-is-headless-browser", "given_title": "", "favorite": "0", "status": "1", "time_added": "1676840969", "time_updated": "1676841121", "time_read": "1676841121", "time_favorited": "0", "sort_id": 24, "resolved_title": "What is a Headless Browser?", "resolved_url": "https://oxylabs.io/blog/what-is-headless-browser", "excerpt": "In short, a headless browser is a web browser without a graphical user interface (GUI). GUI includes digital elements that users interact with, such as buttons, icons, and windows. But there is much more you need to know about a headless browser.", "is_article": "1", "is_index": "0", "has_video": "0", "has_image": "1", "word_count": "904", "lang": "en", "time_to_read": 4, "top_image_url": "https://oxylabs.io/blog/images/2020/10/mika-43E513RKDug-unsplash.jpg", "tags": {"browsers": {"item_id": "3560529951", "tag": "browsers"}, "webdev": {"item_id": "3560529951", "tag": "webdev"}}, "image": {"item_id": "3560529951", "src": "https://oxylabs.io/blog/images/2021/05/john-schnobrich-FlPc9_VocJ4-unsplash.jpg", "width": "2000", "height": "1333"}, "images": {"1": {"item_id": "3560529951", "image_id": "1", "src": "https://oxylabs.io/blog/images/2021/05/john-schnobrich-FlPc9_VocJ4-unsplash.jpg", "width": "2000", "height": "1333", "credit": "", "caption": ""}}, "listen_duration_estimate": 350}, "88476279": {"item_id": "88476279", "resolved_id": "88476279", "given_url": "https://platform.html5.org/", "given_title": "", "favorite": "0", "status": "1", "time_added": "1638240363", "time_updated": "1639700499", "time_read": "1639700499", "time_favorited": "0", "sort_id": 25, "resolved_title": "The Web platform: Browser technologies", "resolved_url": "https://platform.html5.org/", "excerpt": "The Web platform: Browser technologies Core platform HTML ⓤ ⓣ DOM ⓣ ECMAScript ⓣ WebAssembly URL ⓣ Fetch (includes CORS) ⓤ ⓤ ⓣ ⓣ ⚑ ⚑ XMLHttpRequest ⓤ ⓜ ⓣ ⓣ Encoding ⓣ CSS features CSS roadmap ⓤ ⓣ Animations ⓤ ⓜ ⓣ ❢ Background-image options ⓤ ⚑ Borde", "is_article": "0", "is_index": "1", "has_video": "0", "has_image": "0", "word_count": "398", "lang": "en", "tags": {"browsers": {"item_id": "88476279", "tag": "browsers"}, "html": {"item_id": "88476279", "tag": "html"}, "webdev": {"item_id": "88476279", "tag": "webdev"}}, "listen_duration_estimate": 154}, "2350846989": {"item_id": "2350846989", "resolved_id": "2350846989", "given_url": "https://portswigger.net/blog/top-10-web-hacking-techniques-of-2017", "given_title": "Top 10 Web Hacking Techniques of 2017 | Blog", "favorite": "0", "status": "1", "time_added": "1539369338", "time_updated": "1611881990", "time_read": "1539372391", "time_favorited": "0", "sort_id": 26, "resolved_title": "Top 10 Web Hacking Techniques of 2017", "resolved_url": "https://portswigger.net/blog/top-10-web-hacking-techniques-of-2017", "excerpt": "The verdict is in! Following 37 nominations whittled down to a shortlist of 15 by a community vote, our panel of experts has conferred and selected the top 10 web hacking techniques of 2017 (and 2016).", "is_article": "1", "is_index": "0", "has_video": "0", "has_image": "1", "word_count": "1042", "lang": "en", "time_to_read": 5, "top_image_url": "https://portswigger.net/cms/images/37/aa/5d56cc39864a-twittercard-top-10-hacking-techniques-winners-twitter.png", "tags": {"browsers": {"item_id": "2350846989", "tag": "browsers"}, "hacking": {"item_id": "2350846989", "tag": "hacking"}, "security": {"item_id": "2350846989", "tag": "security"}}, "image": {"item_id": "2350846989", "src": "https://portswigger.net/cms/images/66/6a/cd49472a0c43-article-top-10-hacking-techniques-winners-article2.png", "width": "0", "height": "0"}, "images": {"1": {"item_id": "2350846989", "image_id": "1", "src": "https://portswigger.net/cms/images/66/6a/cd49472a0c43-article-top-10-hacking-techniques-winners-article2.png", "width": "0", "height": "0", "credit": "", "caption": ""}}, "listen_duration_estimate": 403}, "2884282295": {"item_id": "2884282295", "resolved_id": "917233715", "given_url": "https://rubyweekly.com/link/83856/ad5e785e3b", "given_title": "", "favorite": "0", "status": "1", "time_added": "1581645909", "time_updated": "1706833159", "time_read": "1582142562", "time_favorited": "0", "sort_id": 27, "resolved_title": "Log outgoing HTTP requests in ruby", "resolved_url": "https://github.com/trusche/httplog", "excerpt": "Log outgoing HTTP requests made from your application. Helps with debugging pesky API error responses, or just generally understanding what's going on under the hood. In theory, it should also work with any library built on top of these.", "is_article": "1", "is_index": "1", "has_video": "0", "has_image": "1", "word_count": "1390", "lang": "en", "time_to_read": 6, "top_image_url": "https://opengraph.githubassets.com/83835d3a2c2911bb09980bdf34f1aa1730638e57ed313556ee55677c488019bc/trusche/httplog", "tags": {"browsers": {"item_id": "2884282295", "tag": "browsers"}, "devops": {"item_id": "2884282295", "tag": "devops"}, "http": {"item_id": "2884282295", "tag": "http"}, "programming": {"item_id": "2884282295", "tag": "programming"}}, "image": {"item_id": "2884282295", "src": "https://camo.githubusercontent.com/0988e672dbe61bd748a1561ec7943a8c84baf02f80dc78071a1b222213f9f148/68747470733a2f2f62616467652e667572792e696f2f72622f687474706c6f672e737667", "width": "0", "height": "0"}, "images": {"1": {"item_id": "2884282295", "image_id": "1", "src": "https://camo.githubusercontent.com/0988e672dbe61bd748a1561ec7943a8c84baf02f80dc78071a1b222213f9f148/68747470733a2f2f62616467652e667572792e696f2f72622f687474706c6f672e737667", "width": "0", "height": "0", "credit": "", "caption": ""}, "2": {"item_id": "2884282295", "image_id": "2", "src": "https://camo.githubusercontent.com/43b0dc722978d0fbeb40961024d5772f8c72d5f2c41c5b6146779e58bf37f29a/68747470733a2f2f7472617669732d63692e6f72672f747275736368652f687474706c6f672e7376673f6272616e63683d6d6173746572", "width": "0", "height": "0", "credit": "", "caption": ""}, "3": {"item_id": "2884282295", "image_id": "3", "src": "https://camo.githubusercontent.com/ec515aa5883d1dd63678af5d9db3860185c0f1896d43f7591761f4c82720cb6f/68747470733a2f2f636f6465636c696d6174652e636f6d2f6769746875622f747275736368652f687474706c6f672e737667", "width": "0", "height": "0", "credit": "", "caption": ""}, "4": {"item_id": "2884282295", "image_id": "4", "src": "https://camo.githubusercontent.com/fc2045372a32632dc09bea1af8f00acb9b41d60ddf201d8ac346ee793d32ee4f/68747470733a2f2f696d672e736869656c64732e696f2f6769746875622f72656c656173652f747275736368652f687474706c6f672e737667", "width": "0", "height": "0", "credit": "", "caption": ""}, "5": {"item_id": "2884282295", "image_id": "5", "src": "https://github.com/trusche/httplog/raw/master/bearer-badge.png", "width": "0", "height": "20", "credit": "", "caption": ""}, "6": {"item_id": "2884282295", "image_id": "6", "src": "https://github.com/trusche/httplog/raw/master/bearer-sponsor.png", "width": "0", "height": "72", "credit": "", "caption": ""}}, "domain_metadata": {"name": "GitHub", "logo": "https://logo.clearbit.com/github.com?size=800", "greyscale_logo": "https://logo.clearbit.com/github.com?size=800&greyscale=true"}, "listen_duration_estimate": 538}, "2907650160": {"item_id": "2907650160", "resolved_id": "2907650160", "given_url": "https://rudism.com/the-brave-browser-is-brilliant/", "given_title": "", "favorite": "1", "status": "1", "time_added": "1583693802", "time_updated": "1611881990", "time_read": "1583698227", "time_favorited": "1583698223", "sort_id": 28, "resolved_title": "The Brave Browser is Brilliant", "resolved_url": "https://rudism.com/the-brave-browser-is-brilliant/", "excerpt": "When I was in grade school (I believe it was grade 7, which would put this somewhere around 1994 or 1995), I created my own currency. It was called Daddy-O dollars, and was minted with pen on post-it notes.", "is_article": "1", "is_index": "0", "has_video": "0", "has_image": "1", "word_count": "2639", "lang": "en", "time_to_read": 12, "tags": {"browsers": {"item_id": "2907650160", "tag": "browsers"}, "prodmgmt": {"item_id": "2907650160", "tag": "prodmgmt"}}, "image": {"item_id": "2907650160", "src": "https://rudism.com/images/brave_1.png", "width": "0", "height": "0"}, "images": {"1": {"item_id": "2907650160", "image_id": "1", "src": "https://rudism.com/images/brave_1.png", "width": "0", "height": "0", "credit": "", "caption": ""}, "2": {"item_id": "2907650160", "image_id": "2", "src": "https://rudism.com/images/brave_2.png", "width": "0", "height": "0", "credit": "", "caption": ""}, "3": {"item_id": "2907650160", "image_id": "3", "src": "https://rudism.com/images/brave_3.png", "width": "0", "height": "0", "credit": "", "caption": ""}}, "listen_duration_estimate": 1022}, "2899403842": {"item_id": "2899403842", "resolved_id": "2899403842", "given_url": "https://searchengineland.com/googles-new-treatment-of-nofollow-links-has-arrived-329862", "given_title": "Google’s new treatment of nofollow links", "favorite": "0", "status": "1", "time_added": "1582915293", "time_updated": "1611881990", "time_read": "1582915611", "time_favorited": "0", "sort_id": 29, "resolved_title": "Google’s new treatment of nofollow links has arrived", "resolved_url": "https://searchengineland.com/googles-new-treatment-of-nofollow-links-has-arrived-329862", "excerpt": "As of Sunday, Mar. 1, Google is treating the nofollow link attribute as a hint, rather than a directive, for crawling and indexing purposes.", "is_article": "1", "is_index": "0", "has_video": "0", "has_image": "0", "word_count": "358", "lang": "en", "amp_url": "https://searchengineland.com/googles-new-treatment-of-nofollow-links-has-arrived-329862/amp", "top_image_url": "https://searchengineland.com/figz/wp-content/seloads/2017/05/google-links-2017c-ss-1920.jpg", "tags": {"browsers": {"item_id": "2899403842", "tag": "browsers"}, "webdev": {"item_id": "2899403842", "tag": "webdev"}}, "authors": {"107686646": {"item_id": "2899403842", "author_id": "107686646", "name": "George Nguyen", "url": "https://searchengineland.com/author/george-nguyen"}}, "domain_metadata": {"name": "Search Engine Land", "logo": "https://logo.clearbit.com/searchengineland.com?size=800", "greyscale_logo": "https://logo.clearbit.com/searchengineland.com?size=800&greyscale=true"}, "listen_duration_estimate": 139}, "3839695625": {"item_id": "3839695625", "resolved_id": "3839695633", "given_url": "https://tech.slashdot.org/story/23/04/04/2128239/chrome-112-released-with-wasm-garbage-collection-trial-css-nesting?utm_source=rss1.0mainlinkanon&utm_medium=feed", "given_title": "Chrome 112 Released With WASM Garbage Collection Trial, CSS Nesting", "favorite": "0", "status": "1", "time_added": "1680687200", "time_updated": "1680712796", "time_read": "1680712796", "time_favorited": "0", "sort_id": 30, "resolved_title": "Chrome 112 Released With WASM Garbage Collection Trial, CSS Nesting", "resolved_url": "https://tech.slashdot.org/story/23/04/04/2128239/chrome-112-released-with-wasm-garbage-collection-trial-css-nesting", "excerpt": "Google today promoted the Chrome 112 web browser to their stable channel on all supported platforms. Phoronix reports: Starting as an origin trial with Chrome 112 is WebAssembly (WASM) Garbage Collection support.", "is_article": "1", "is_index": "0", "has_video": "0", "has_image": "0", "word_count": "219", "lang": "en", "top_image_url": "https://a.fsdn.com/sd/topics/chrome_64.png", "tags": {"browsers": {"item_id": "3839695625", "tag": "browsers"}, "css": {"item_id": "3839695625", "tag": "css"}, "webdev": {"item_id": "3839695625", "tag": "webdev"}}, "authors": {"47802700": {"item_id": "3839695625", "author_id": "47802700", "name": "BeauHD", "url": "https://twitter.com/BeauHD"}}, "domain_metadata": {"name": "Slashdot", "logo": "https://logo.clearbit.com/slashdot.org?size=800", "greyscale_logo": "https://logo.clearbit.com/slashdot.org?size=800&greyscale=true"}, "listen_duration_estimate": 85}, "3892267962": {"item_id": "3892267962", "resolved_id": "3892267962", "given_url": "https://thehackernews.com/2023/06/the-power-of-browser-fingerprinting.html", "given_title": "The Power of Browser Fingerprinting: Personalized UX, Fraud Detection, and ", "favorite": "0", "status": "1", "time_added": "1687536821", "time_updated": "1687639216", "time_read": "1687639216", "time_favorited": "0", "sort_id": 31, "resolved_title": "The Power of Browser Fingerprinting: Personalized UX, Fraud Detection, and Secure Logins", "resolved_url": "https://thehackernews.com/2023/06/the-power-of-browser-fingerprinting.html", "excerpt": "The case for browser fingerprinting: personalizing user experience, improving fraud detection, and optimizing login security Have you ever heard of browser fingerprinting? You should! It's an online user identification technique that collects information about a visitor's web browser and its configu", "is_article": "1", "is_index": "0", "has_video": "0", "has_image": "1", "word_count": "1277", "lang": "en", "time_to_read": 6, "top_image_url": "https://thehackernews.com/new-images/img/b/R29vZ2xl/AVvXsEhcGkSeO7M2TPhfX4hQk1oMBagUlSTZzPPq--z0p3C9i85Fvsxo8aOQAN0vmrtQ4T_Mc8vQ1F6_HKQ1d8T1x0sML6MFYG7p22zJQSPyqYLEVtMgMDT94wJsRXMiWUoT_Sf4CJMBMkZTqhvO_6jkbg77NZNw6NQWwNRUgUSqIoevXdUUMRQMX8gCIGvj1LI/s728-e3650/browser-fingerprint.jpg", "tags": {"browsers": {"item_id": "3892267962", "tag": "browsers"}, "webdev": {"item_id": "3892267962", "tag": "webdev"}}, "authors": {"183072421": {"item_id": "3892267962", "author_id": "183072421", "name": "well documented", "url": "https://blog.superhuman.com/why-do-people-use-dark-mode/"}}, "image": {"item_id": "3892267962", "src": "https://thehackernews.com/new-images/img/b/R29vZ2xl/AVvXsEhcGkSeO7M2TPhfX4hQk1oMBagUlSTZzPPq--z0p3C9i85Fvsxo8aOQAN0vmrtQ4T_Mc8vQ1F6_HKQ1d8T1x0sML6MFYG7p22zJQSPyqYLEVtMgMDT94wJsRXMiWUoT_Sf4CJMBMkZTqhvO_6jkbg77NZNw6NQWwNRUgUSqIoevXdUUMRQMX8gCIGvj1LI/s728-e365/browser-fingerprint.jpg", "width": "0", "height": "0"}, "images": {"1": {"item_id": "3892267962", "image_id": "1", "src": "https://thehackernews.com/new-images/img/b/R29vZ2xl/AVvXsEhcGkSeO7M2TPhfX4hQk1oMBagUlSTZzPPq--z0p3C9i85Fvsxo8aOQAN0vmrtQ4T_Mc8vQ1F6_HKQ1d8T1x0sML6MFYG7p22zJQSPyqYLEVtMgMDT94wJsRXMiWUoT_Sf4CJMBMkZTqhvO_6jkbg77NZNw6NQWwNRUgUSqIoevXdUUMRQMX8gCIGvj1LI/s728-e365/browser-fingerprint.jpg", "width": "0", "height": "0", "credit": "", "caption": ""}}, "listen_duration_estimate": 494}, "44755720": {"item_id": "44755720", "resolved_id": "44755720", "given_url": "https://wiki.mozilla.org/Fingerprinting", "given_title": "", "favorite": "0", "status": "1", "time_added": "1606610118", "time_updated": "1611881990", "time_read": "1608290480", "time_favorited": "0", "sort_id": 32, "resolved_title": "Fingerprinting", "resolved_url": "https://wiki.mozilla.org/Fingerprinting", "excerpt": "The EFF published an excellent study in May, detailing some of the various methods of fingerprinting a browser. See http://www.eff.org/deeplinks/2010/05/every-browser-unique-results-fom-panopticlick. They found that, over their study of around 1 million visits to their study website, 83.", "is_article": "1", "is_index": "1", "has_video": "0", "has_image": "0", "word_count": "2095", "lang": "en", "time_to_read": 10, "tags": {"browsers": {"item_id": "44755720", "tag": "browsers"}}, "authors": {"11365": {"item_id": "44755720", "author_id": "11365", "name": "JS", "url": ""}}, "listen_duration_estimate": 811}, "3645490486": {"item_id": "3645490486", "resolved_id": "3645490486", "given_url": "https://www.bleepingcomputer.com/news/software/privacy-focused-brave-search-grew-by-5-000-percent-in-a-year/", "given_title": "", "favorite": "0", "status": "1", "time_added": "1655933334", "time_updated": "1655938807", "time_read": "1655938806", "time_favorited": "0", "sort_id": 33, "resolved_title": "Privacy-focused Brave Search grew by 5,000% in a year", "resolved_url": "https://www.bleepingcomputer.com/news/software/privacy-focused-brave-search-grew-by-5-000-percent-in-a-year/", "excerpt": "Brave Search, the browser developer's privacy-centric Internet search engine, is celebrating its first anniversary after surpassing 2.5 billion queries and seeing almost 5,000% growth in a year.", "is_article": "1", "is_index": "0", "has_video": "0", "has_image": "1", "word_count": "519", "lang": "en", "amp_url": "https://www.bleepingcomputer.com/news/software/privacy-focused-brave-search-grew-by-5-000-percent-in-a-year/amp/", "top_image_url": "https://www.bleepstatic.com/content/hl-images/2022/06/22/brave-search-header.jpg", "tags": {"browsers": {"item_id": "3645490486", "tag": "browsers"}, "privacy": {"item_id": "3645490486", "tag": "privacy"}, "search": {"item_id": "3645490486", "tag": "search"}}, "authors": {"157607840": {"item_id": "3645490486", "author_id": "157607840", "name": "Bill Toulas", "url": "https://www.bleepingcomputer.com/author/bill-toulas/"}}, "image": {"item_id": "3645490486", "src": "https://www.bleepstatic.com/content/hl-images/2022/06/22/brave-search-header.jpg", "width": "1600", "height": "900"}, "images": {"1": {"item_id": "3645490486", "image_id": "1", "src": "https://www.bleepstatic.com/content/hl-images/2022/06/22/brave-search-header.jpg", "width": "1600", "height": "900", "credit": "", "caption": ""}, "2": {"item_id": "3645490486", "image_id": "2", "src": "https://www.bleepstatic.com/images/news/u/1220909/Diagrams/monthly-diagram.png", "width": "984", "height": "497", "credit": "", "caption": ""}, "3": {"item_id": "3645490486", "image_id": "3", "src": "https://www.bleepstatic.com/images/news/u/1220909/Software/goggle.png", "width": "572", "height": "600", "credit": "Brave", "caption": "Brave Search results with the Tech Blogs Goggle"}}, "domain_metadata": {"name": "BleepingComputer", "logo": "https://logo.clearbit.com/bleepingcomputer.com?size=800", "greyscale_logo": "https://logo.clearbit.com/bleepingcomputer.com?size=800&greyscale=true"}, "listen_duration_estimate": 201}, "3018529517": {"item_id": "3018529517", "resolved_id": "3018529517", "given_url": "https://www.debugbear.com/blog/2020-chrome-extension-performance-report", "given_title": "2020 Chrome Extension Performance Report | DebugBear", "favorite": "1", "status": "1", "time_added": "1592311637", "time_updated": "1611881990", "time_read": "1592314663", "time_favorited": "1592314648", "sort_id": 34, "resolved_title": "2020 Chrome Extension Performance Report", "resolved_url": "https://www.debugbear.com/blog/2020-chrome-extension-performance-report", "excerpt": "The main metrics I'll consider are CPU consumption, memory consumption, and whether the extension makes pages render more slowly. Here's a list of all tested extensions and their results (this link now shows 2021 data).", "is_article": "1", "is_index": "0", "has_video": "0", "has_image": "1", "word_count": "2248", "lang": "en", "time_to_read": 10, "top_image_url": "https://www.debugbear.com/public/blog/2020-chrome-extension-performance-report/chrome-extension-page-cpu-time.png", "tags": {"browsers": {"item_id": "3018529517", "tag": "browsers"}, "javascript": {"item_id": "3018529517", "tag": "javascript"}, "webdev": {"item_id": "3018529517", "tag": "webdev"}}, "image": {"item_id": "3018529517", "src": "https://www.debugbear.com/assets/images/chrome-extension-page-cpu-time-28566300d6bc08bec7f4bc452c4a3e90.png", "width": "862", "height": "633"}, "images": {"1": {"item_id": "3018529517", "image_id": "1", "src": "https://www.debugbear.com/assets/images/chrome-extension-page-cpu-time-28566300d6bc08bec7f4bc452c4a3e90.png", "width": "862", "height": "633", "credit": "", "caption": ""}, "2": {"item_id": "3018529517", "image_id": "2", "src": "https://www.debugbear.com/assets/images/evernote-page-trace-7e9c171c9ad8c3d956a29ad2a2b03a2d.png", "width": "498", "height": "277", "credit": "", "caption": ""}, "3": {"item_id": "3018529517", "image_id": "3", "src": "https://www.debugbear.com/assets/images/extension-fcp-ccb2a7dbd883a05b2025229db75e4b6c.png", "width": "766", "height": "592", "credit": "", "caption": ""}, "4": {"item_id": "3018529517", "image_id": "4", "src": "https://www.debugbear.com/assets/images/safeprice-trace-31f70d713430470f619d685afb126409.png", "width": "645", "height": "298", "credit": "", "caption": ""}, "5": {"item_id": "3018529517", "image_id": "5", "src": "https://www.debugbear.com/assets/images/background-page-cpu-51ef7d6b460de230d927378f94e6993c.png", "width": "745", "height": "401", "credit": "", "caption": ""}, "6": {"item_id": "3018529517", "image_id": "6", "src": "https://www.debugbear.com/assets/images/background-page-cpu-apple-1a0e71facd7c93f9f1b7e95353f3e322.png", "width": "809", "height": "588", "credit": "", "caption": ""}, "7": {"item_id": "3018529517", "image_id": "7", "src": "https://www.debugbear.com/assets/images/top-100-extension-browser-memory-consumption-33d3180443e7bc2089af7a4c20b8eca5.png", "width": "822", "height": "557", "credit": "", "caption": ""}, "8": {"item_id": "3018529517", "image_id": "8", "src": "https://www.debugbear.com/assets/images/amazon-assistant-subframes-2b457502ae0b44c525b29837c10ca5c9.png", "width": "1214", "height": "540", "credit": "", "caption": ""}, "9": {"item_id": "3018529517", "image_id": "9", "src": "https://www.debugbear.com/assets/images/page-cpu-top-1000-909c51f29cabe63e151fc25fef3d2408.png", "width": "852", "height": "622", "credit": "", "caption": ""}, "10": {"item_id": "3018529517", "image_id": "10", "src": "https://www.debugbear.com/assets/images/vigia-de-preco-trace-fd235ee65e27958125b9952afefb5449.png", "width": "973", "height": "432", "credit": "", "caption": ""}, "11": {"item_id": "3018529517", "image_id": "11", "src": "https://www.debugbear.com/assets/images/rendering-delays-top-1000-721817d75261c8a0855d051bbad4f461.png", "width": "741", "height": "463", "credit": "", "caption": ""}, "12": {"item_id": "3018529517", "image_id": "12", "src": "https://www.debugbear.com/assets/images/top-1000-background-page-cpu-2b3e728d9cc9f950be11924f8b3afcb0.png", "width": "927", "height": "588", "credit": "", "caption": ""}, "13": {"item_id": "3018529517", "image_id": "13", "src": "https://www.debugbear.com/assets/images/traffic-light-bg-cpu-66f41ff2f41cea21dedda3ca7e536cc8.png", "width": "697", "height": "491", "credit": "", "caption": ""}, "14": {"item_id": "3018529517", "image_id": "14", "src": "https://www.debugbear.com/assets/images/top-1000-extension-browser-memeory-488920420951f5e863acb805379fcc4b.png", "width": "833", "height": "521", "credit": "", "caption": ""}, "15": {"item_id": "3018529517", "image_id": "15", "src": "https://www.debugbear.com/assets/images/ad-blocker-page-cpu-caf86a4f2347c07d99178a9fa7bde267.png", "width": "810", "height": "670", "credit": "", "caption": ""}, "16": {"item_id": "3018529517", "image_id": "16", "src": "https://www.debugbear.com/assets/images/ad-blocker-requests-acb76a6025aefe182e3fc6c4a8279c52.png", "width": "657", "height": "606", "credit": "", "caption": ""}, "17": {"item_id": "3018529517", "image_id": "17", "src": "https://www.debugbear.com/assets/images/ad-blocker-bg-cpu-d62e3c2c150e12e5b2b4e576d1c676ef.png", "width": "800", "height": "675", "credit": "", "caption": ""}, "18": {"item_id": "3018529517", "image_id": "18", "src": "https://www.debugbear.com/assets/images/ad-blocker-browser-memory-a98e1245bec3da6d1057bea908d48a88.png", "width": "837", "height": "670", "credit": "", "caption": ""}, "19": {"item_id": "3018529517", "image_id": "19", "src": "https://www.debugbear.com/assets/images/devtools-page-cpu-c033169ade5b318cfbd5bb32406568b3.png", "width": "852", "height": "561", "credit": "", "caption": ""}, "20": {"item_id": "3018529517", "image_id": "20", "src": "https://www.debugbear.com/assets/images/devtools-fcp-b721ec4ac87670fc368b1045c3a98e21.png", "width": "760", "height": "522", "credit": "", "caption": ""}, "21": {"item_id": "3018529517", "image_id": "21", "src": "https://www.debugbear.com/assets/images/axe-trace-7dffa69239b1d519a5e1181643c22576.png", "width": "610", "height": "328", "credit": "", "caption": ""}, "22": {"item_id": "3018529517", "image_id": "22", "src": "https://www.debugbear.com/assets/images/devtools-bg-cpu-bf4da39d846499ffeb7a38faeb41b511.png", "width": "799", "height": "530", "credit": "", "caption": ""}, "23": {"item_id": "3018529517", "image_id": "23", "src": "https://www.debugbear.com/assets/images/devtools-browser-memory-39969d2c1c0426a8d7b68742621d1786.png", "width": "838", "height": "536", "credit": "", "caption": ""}}, "listen_duration_estimate": 870}, "3985825152": {"item_id": "3985825152", "resolved_id": "3985825152", "given_url": "https://www.howtogeek.com/the-best-reason-to-use-firefox-is-sync-that-actually-works/", "given_title": "The Best Reason to Use Firefox Is Sync That Actually Works", "favorite": "0", "status": "1", "time_added": "1703785811", "time_updated": "1703796337", "time_read": "1703796337", "time_favorited": "0", "sort_id": 35, "resolved_title": "The Best Reason to Use Firefox Is Sync That Actually Works", "resolved_url": "https://www.howtogeek.com/the-best-reason-to-use-firefox-is-sync-that-actually-works/", "excerpt": "With so much of our digital lives neatly saved and synced in our web browser of choice, the idea of switching to a different one can feel as daunting as moving to a new home. Chrome Sync, in particular, has kept many people using Chrome.", "is_article": "1", "is_index": "0", "has_video": "0", "has_image": "0", "word_count": "640", "lang": "en", "time_to_read": 3, "top_image_url": "https://static1.howtogeekimages.com/wordpress/wp-content/uploads/2023/12/firefox-hero-1.png", "tags": {"browsers": {"item_id": "3985825152", "tag": "browsers"}}, "authors": {"138070553": {"item_id": "3985825152", "author_id": "138070553", "name": "Joe Fedewa", "url": "https://www.howtogeek.com/author/joefedewa/"}}, "domain_metadata": {"name": "How-To Geek", "logo": "https://logo.clearbit.com/howtogeek.com?size=800", "greyscale_logo": "https://logo.clearbit.com/howtogeek.com?size=800&greyscale=true"}, "listen_duration_estimate": 248}, "38622084": {"item_id": "38622084", "resolved_id": "103760500", "given_url": "https://www.mozilla.org/firefox/", "given_title": "", "favorite": "0", "status": "1", "time_added": "1638240363", "time_updated": "1639521172", "time_read": "1639521172", "time_favorited": "0", "sort_id": 36, "resolved_title": "Firefox is just the beginning.", "resolved_url": "https://www.mozilla.org/en-US/firefox/", "excerpt": "Firefox is more than a browser. Learn more about Firefox products that handle your data with respect and are built for privacy anywhere you go online.", "is_article": "0", "is_index": "0", "has_video": "0", "has_image": "0", "word_count": "0", "lang": "en", "top_image_url": "https://www.mozilla.org/media/img/firefox/template/page-image-master.1b6efe3d5631.jpg", "tags": {"browsers": {"item_id": "38622084", "tag": "browsers"}, "webdev": {"item_id": "38622084", "tag": "webdev"}}, "domain_metadata": {"name": "Mozilla", "logo": "https://logo.clearbit.com/mozilla.org?size=800", "greyscale_logo": "https://logo.clearbit.com/mozilla.org?size=800&greyscale=true"}, "listen_duration_estimate": 0}, "2110983437": {"item_id": "2110983437", "resolved_id": "2110983437", "given_url": "https://www.noupe.com/design/headless-browsers-kill-web-design.html", "given_title": "Fade to Grey: Will Headless Browsers Kill Web Design?", "favorite": "0", "status": "1", "time_added": "1520857504", "time_updated": "1611881990", "time_read": "1520874695", "time_favorited": "0", "sort_id": 37, "resolved_title": "", "resolved_url": "https://www.noupe.com/design/headless-browsers-kill-web-design.html", "excerpt": "", "is_article": "0", "is_index": "0", "has_video": "0", "has_image": "0", "word_count": "0", "lang": "en", "tags": {"browsers": {"item_id": "2110983437", "tag": "browsers"}, "webdev": {"item_id": "2110983437", "tag": "webdev"}}, "listen_duration_estimate": 0}, "4002499327": {"item_id": "4002499327", "resolved_id": "4002499327", "given_url": "https://www.practicalecommerce.com/privacy-tactics-complicate-ecommerce-marketing", "given_title": "Privacy Tactics Complicate Ecommerce Marketing", "favorite": "0", "status": "1", "time_added": "1706877358", "time_updated": "1706930527", "time_read": "1706930527", "time_favorited": "0", "sort_id": 38, "resolved_title": "Privacy Tactics Complicate Ecommerce Marketing", "resolved_url": "https://www.practicalecommerce.com/privacy-tactics-complicate-ecommerce-marketing", "excerpt": "Leading web browsers and email clients are doing more to stop user tracking, effectively reducing or eliminating the conversion signals many marketers depend on. Advertisers love connecting ads with sales. That’s how they measure return on advertising spend, a key metric.", "is_article": "1", "is_index": "0", "has_video": "0", "has_image": "0", "word_count": "656", "lang": "en", "time_to_read": 3, "top_image_url": "https://www.practicalecommerce.com/wp-content/uploads/2024/01/012724-featured-ublock.jpg", "tags": {"browsers": {"item_id": "4002499327", "tag": "browsers"}, "ecommerce": {"item_id": "4002499327", "tag": "ecommerce"}}, "authors": {"89778274": {"item_id": "4002499327", "author_id": "89778274", "name": "Editorial Policy", "url": "https://www.practicalecommerce.com/editorial-policy"}}, "listen_duration_estimate": 254}, "1656944466": {"item_id": "1656944466", "resolved_id": "1656944466", "given_url": "https://www.smashingmagazine.com/articles/", "given_title": "", "favorite": "0", "status": "1", "time_added": "1677019521", "time_updated": "1677024838", "time_read": "1677024838", "time_favorited": "0", "sort_id": 39, "resolved_title": "Articles — Smashing Magazine", "resolved_url": "https://www.smashingmagazine.com/articles/", "excerpt": "July 31, 2021 — New month, new wallpapers! In this post, you’ll find unique and inspiring wallpapers for August 2021. Created with love by the community for the community, they come in versions with and without a calendar for the month. Read more…", "is_article": "0", "is_index": "0", "has_video": "0", "has_image": "0", "word_count": "685", "lang": "en", "time_to_read": 3, "top_image_url": "https:", "tags": {"browsers": {"item_id": "1656944466", "tag": "browsers"}, "css": {"item_id": "1656944466", "tag": "css"}, "html": {"item_id": "1656944466", "tag": "html"}, "svg": {"item_id": "1656944466", "tag": "svg"}, "ui-ux": {"item_id": "1656944466", "tag": "ui-ux"}, "webdev": {"item_id": "1656944466", "tag": "webdev"}}, "authors": {"79456203": {"item_id": "1656944466", "author_id": "79456203", "name": "Cosima Mielke", "url": "https://www.smashingmagazine.com/author/cosima-mielke"}}, "domain_metadata": {"name": "Smashing Magazine", "logo": "https://logo.clearbit.com/smashingmagazine.com?size=800", "greyscale_logo": "https://logo.clearbit.com/smashingmagazine.com?size=800&greyscale=true"}, "listen_duration_estimate": 265}, "3582422004": {"item_id": "3582422004", "resolved_id": "3582422004", "given_url": "https://www.techradar.com/news/this-browser-youve-never-heard-of-is-now-worth-a-billion-dollars", "given_title": "", "favorite": "0", "status": "1", "time_added": "1648305160", "time_updated": "1648342968", "time_read": "1648342968", "time_favorited": "0", "sort_id": 40, "resolved_title": "This browser you've never heard of is now worth a billion dollars", "resolved_url": "https://www.techradar.com/news/this-browser-youve-never-heard-of-is-now-worth-a-billion-dollars", "excerpt": "Island exited stealth mode in early February, but has already achieved unicorn status courtesy of a $115 million Series B funding round that valued the company at $1.3 billion.", "is_article": "1", "is_index": "0", "has_video": "0", "has_image": "0", "word_count": "435", "lang": "en", "top_image_url": "https://cdn.mos.cms.futurecdn.net/SyufUSFP35BxnL9HdGAHwJ-1200-80.png", "tags": {"browsers": {"item_id": "3582422004", "tag": "browsers"}, "malware": {"item_id": "3582422004", "tag": "malware"}, "webdev": {"item_id": "3582422004", "tag": "webdev"}}, "authors": {"105438300": {"item_id": "3582422004", "author_id": "105438300", "name": "Joel Khalili", "url": ""}}, "domain_metadata": {"name": "TechRadar", "logo": "https://logo.clearbit.com/techradar.com?size=800", "greyscale_logo": "https://logo.clearbit.com/techradar.com?size=800&greyscale=true"}, "listen_duration_estimate": 168}}, "error": nil, "search_meta": {"search_type": "normal"}, "since": 1709419191}