{"status": 1, "complete": 1, "list": {"1687292448": {"item_id": "1687292448", "resolved_id": "1687292448", "given_url": "https://www.vagrantup.com/intro/index.html", "given_title": "", "favorite": "0", "status": "1", "time_added": "1638240697", "time_updated": "1706833159", "time_read": "1639332988", "time_favorited": "0", "sort_id": 0, "resolved_title": "Introduction : Vagrant by HashiCorp", "resolved_url": "https://www.vagrantup.com/intro/index.html", "excerpt": "Vagrant is a tool for building and managing virtual machine environments in a single workflow. With an easy-to-use workflow and focus on automation, Vagrant lowers development environment setup time, increases production parity, and makes the \"works on my machine\" excuse a relic of the past.", "is_article": "1", "is_index": "1", "has_video": "0", "has_image": "0", "word_count": "457", "lang": "en", "top_image_url": "https://www.vagrantup.com/img/og-image.png", "tags": {"devops": {"item_id": "1687292448", "tag": "devops"}, "programming": {"item_id": "1687292448", "tag": "programming"}, "vagrant": {"item_id": "1687292448", "tag": "vagrant"}}, "listen_duration_estimate": 177}, "3076652704": {"item_id": "3076652704", "resolved_id": "3076652704", "given_url": "https://learn.hashicorp.com/collections/vagrant/getting-started", "given_title": "", "favorite": "0", "status": "1", "time_added": "1638240697", "time_updated": "1660827285", "time_read": "1638409710", "time_favorited": "0", "sort_id": 1, "resolved_title": "Getting Started", "resolved_url": "https://learn.hashicorp.com/collections/vagrant/getting-started", "excerpt": "The Vagrant getting started tutorials will walk you through creating your first development environment with Vagrant. This... Install Vagrant by visiting the Vagrant downloads page and downloading the appropriate installer or package for your platform....", "is_article": "0", "is_index": "0", "has_video": "0", "has_image": "0", "word_count": "294", "lang": "en", "top_image_url": "https://www.datocms-assets.com/2885/1622161215-learn-card-2x.jpg", "tags": {"devops": {"item_id": "3076652704", "tag": "devops"}, "vagrant": {"item_id": "3076652704", "tag": "vagrant"}}, "listen_duration_estimate": 114}, "1810192525": {"item_id": "1810192525", "resolved_id": "1810192553", "given_url": "https://github.com/openstackcookbook/vagrant-openstack", "given_title": "OpenStackCookbook/vagrant-openstack: Vagrant OpenStack-Ansible Environment ", "favorite": "0", "status": "1", "time_added": "1560028429", "time_updated": "1586296702", "time_read": "1567124028", "time_favorited": "0", "sort_id": 2, "resolved_title": "vagrant-openstack (Latest Master: Stein)", "resolved_url": "https://github.com/OpenStackCookbook/vagrant-openstack", "excerpt": "Vagrant environment that uses OpenStack Ansible for deploying OpenStack. Contributors: Time to deploy: 1 - 2 hours.", "is_article": "1", "is_index": "0", "has_video": "0", "has_image": "0", "word_count": "474", "lang": "en", "top_image_url": "https://opengraph.githubassets.com/ad1dfc9a6c98edbda649be33cc13a98389e7d2dda47aa9768e26ea4ee6f60ea4/OpenStackCookbook/vagrant-openstack", "tags": {"vagrant": {"item_id": "1810192525", "tag": "vagrant"}}, "domain_metadata": {"name": "GitHub", "logo": "https://logo.clearbit.com/github.com?size=800", "greyscale_logo": "https://logo.clearbit.com/github.com?size=800&greyscale=true"}, "listen_duration_estimate": 183}, "1672666485": {"item_id": "1672666485", "resolved_id": "1672666485", "given_url": "https://stackoverflow.com/questions/23690124/vagrant-up-timeout", "given_title": "Vagrant up timeout - Stack Overflow", "favorite": "1", "status": "1", "time_added": "1585424652", "time_updated": "1660827285", "time_read": "1585669418", "time_favorited": "1585438325", "sort_id": 3, "resolved_title": "Vagrant up timeout", "resolved_url": "https://stackoverflow.com/questions/23690124/vagrant-up-timeout", "excerpt": "Having some issues to get my vagrant up, Got the box, run vagrant init and after vagrant up command I get this message. Any suggestions?", "is_article": "1", "is_index": "0", "has_video": "0", "has_image": "1", "word_count": "1301", "lang": "en", "time_to_read": 6, "top_image_url": "https://cdn.sstatic.net/Sites/stackoverflow/Img/apple-touch-icon@2.png?v=73d79a89bded", "tags": {"devops": {"item_id": "1672666485", "tag": "devops"}, "vagrant": {"item_id": "1672666485", "tag": "vagrant"}, "virtualbox": {"item_id": "1672666485", "tag": "virtualbox"}}, "authors": {"69019986": {"item_id": "1672666485", "author_id": "69019986", "name": "ROMANIA_engineer", "url": "https://stackoverflow.com/users/3885376/romania-engineer"}, "164953358": {"item_id": "1672666485", "author_id": "164953358", "name": "Merlo", "url": "https://stackoverflow.com/users/3566468/merlo"}}, "image": {"item_id": "1672666485", "src": "https://i.stack.imgur.com/khWqP.jpg?s=64&g=1", "width": "32", "height": "32"}, "images": {"1": {"item_id": "1672666485", "image_id": "1", "src": "https://i.stack.imgur.com/khWqP.jpg?s=64&g=1", "width": "32", "height": "32", "credit": "", "caption": ""}, "2": {"item_id": "1672666485", "image_id": "2", "src": "https://i.stack.imgur.com/dWu1g.jpg?s=64&g=1", "width": "32", "height": "32", "credit": "", "caption": ""}, "3": {"item_id": "1672666485", "image_id": "3", "src": "https://i.stack.imgur.com/Pq0wF.png", "width": "0", "height": "0", "credit": "", "caption": ""}, "4": {"item_id": "1672666485", "image_id": "4", "src": "https://i.stack.imgur.com/Daf6l.jpg?s=64&g=1", "width": "32", "height": "32", "credit": "", "caption": ""}, "5": {"item_id": "1672666485", "image_id": "5", "src": "https://i.stack.imgur.com/pr6zf.jpg?s=64&g=1", "width": "32", "height": "32", "credit": "", "caption": ""}, "6": {"item_id": "1672666485", "image_id": "6", "src": "https://i.stack.imgur.com/b0wCO.png?s=64&g=1", "width": "32", "height": "32", "credit": "", "caption": ""}}, "domain_metadata": {"name": "Stack Overflow", "logo": "https://logo.clearbit.com/stackoverflow.com?size=800", "greyscale_logo": "https://logo.clearbit.com/stackoverflow.com?size=800&greyscale=true"}, "listen_duration_estimate": 504}, "1392730158": {"item_id": "1392730158", "resolved_id": "1392730158", "given_url": "https://devopslibrary.com/lessons/what-is-vagrant/", "given_title": "What is Vagrant? - DevOps Library", "favorite": "0", "status": "1", "time_added": "1600903265", "time_updated": "1660827285", "time_read": "1604362381", "time_favorited": "0", "sort_id": 4, "resolved_title": "What is Vagrant?", "resolved_url": "https://www.devopslibrary.com/lessons/what-is-vagrant", "excerpt": "Hello, this is Samantha with the DevOps Library, and today we’re going to begin our short course on Vagrant. If you’ve already seen our previous video on vagrant feel free to skip ahead to the more advanced topics in the course.", "is_article": "1", "is_index": "0", "has_video": "1", "has_image": "1", "word_count": "596", "lang": "en", "time_to_read": 3, "top_image_url": "https://www.devopslibrary.com/images/default.png", "tags": {"devops": {"item_id": "1392730158", "tag": "devops"}, "vagrant": {"item_id": "1392730158", "tag": "vagrant"}}, "authors": {"56221695": {"item_id": "1392730158", "author_id": "56221695", "name": "About Us", "url": "https://www.devopslibrary.com/about/"}}, "image": {"item_id": "1392730158", "src": "http://img.youtube.com/vi/aUew6WauUsI/0.jpg", "width": "480", "height": "360"}, "images": {"1": {"item_id": "1392730158", "image_id": "1", "src": "http://img.youtube.com/vi/aUew6WauUsI/0.jpg", "width": "480", "height": "360", "credit": "", "caption": ""}}, "videos": {"1": {"item_id": "1392730158", "video_id": "1", "src": "https://www.youtube.com/embed/aUew6WauUsI", "width": "768", "height": "576", "type": "1", "vid": "aUew6WauUsI", "length": "0"}}, "listen_duration_estimate": 231}}, "error": nil, "search_meta": {"search_type": "normal"}, "since": 1709934977}